cricinfo/__init__.py
cricinfo/cricinfo.py
cricinfo/match_format.py
cricinfo/team.py
cricinfo/helpers/__init__.py
cricinfo/helpers/data_sanitizer.py
cricinfo/helpers/request_helper.py
cricinfo/helpers/stat_type.py
cricinfo/services/__init__.py
cricinfo/services/cricinfo_service.py
tests/__init__.py
tests/test_cricinfo.py
tests/test_match_format.py
tests/test_team.py
tests/test_helpers/__init__.py
tests/test_helpers/test_data_sanitizer.py
tests/test_helpers/test_request_helper.py
tests/test_services/__init__.py
tests/test_services/test_cricinfo_service.py
cricinfo_stats-1.0.4.dist-info/LICENSE
cricinfo_stats-1.0.4.dist-info/METADATA
cricinfo_stats-1.0.4.dist-info/WHEEL
cricinfo_stats-1.0.4.dist-info/top_level.txt
cricinfo_stats-1.0.4.dist-info/RECORD
