Metadata-Version: 2.1
Name: cricinfo-stats
Version: 1.0.4
Summary: Python/Pandas Client for https://www.espncricinfo.com stats
Home-page: https://github.com/aaraza/cricinfo
Author: Ali Raza
Author-email: aaraza1995@gmail.com
Classifier: Programming Language :: Python :: 3
Classifier: License :: OSI Approved :: MIT License
Classifier: Operating System :: OS Independent
Requires-Python: >=3.7
License-File: LICENSE
Requires-Dist: pandas>=2.2.3
Requires-Dist: requests>=2.32.3
Requires-Dist: lxml>=5.3.0
